blobopera/__init__.py
blobopera/__main__.py
blobopera/backend/__init__.py
blobopera/backend/backend.py
blobopera/command/__init__.py
blobopera/command/common.py
blobopera/command/jitter.py
blobopera/command/libretto.py
blobopera/command/recording.py
blobopera/jitter.py
blobopera/languages/__init__.py
blobopera/languages/generic.py
blobopera/languages/language.py
blobopera/languages/random.py
blobopera/libretto.py
blobopera/location.py
blobopera/phoneme.py
blobopera/recording.py
blobopera/theme.py
blobopera-1.0.3.dist-info/METADATA
blobopera-1.0.3.dist-info/entry_points.txt
blobopera-1.0.3.dist-info/WHEEL
blobopera-1.0.3.dist-info/LICENSE
blobopera-1.0.3.dist-info/RECORD
