Metadata-Version: 2.1
Name: blobopera
Version: 1.0.3
Summary: Unofficial toolkit for Google Arts & Culture Blob Opera
Home-page: https://github.com/0x2b3bfa0/python-blobopera
License: GPL-3.0-or-later
Author: Helio Machado
Author-email: 0x2b3bfa0@googlemail.com
Maintainer: Helio Machado
Maintainer-email: 0x2b3bfa0@googlemail.com
Requires-Python: >=3.9,<4.0
Classifier: License :: OSI Approved :: GNU General Public License v3 or later (GPLv3+)
Classifier: Programming Language :: Python :: 3
Classifier: Programming Language :: Python :: 3.9
Classifier: Programming Language :: Python :: 3.10
Classifier: Programming Language :: Python :: 3.11
Requires-Dist: colorama (>=0.4.4,<0.5.0)
Requires-Dist: matplotlib (>=3.3.3,<4.0.0)
Requires-Dist: more-itertools (>=8.6.0,<9.0.0)
Requires-Dist: music21 (>=6.3.0,<7.0.0)
Requires-Dist: numpy (>=1.19.4,<2.0.0)
Requires-Dist: proto-plus (>=1.13.0,<2.0.0)
Requires-Dist: protobuf (==3.14.0)
Requires-Dist: requests (>=2.25.1,<3.0.0)
Requires-Dist: typer[all] (>=0.3.2,<0.4.0)
Project-URL: Documentation, https://0x2b3bfa0.github.io/python-blobopera
Project-URL: Repository, https://github.com/0x2b3bfa0/python-blobopera
